LICENSE
MANIFEST.in
NOTICE
Pipfile
Pipfile.lock
README.md
setup.py
bin/data-simulator
data_simulator.egg-info/PKG-INFO
data_simulator.egg-info/SOURCES.txt
data_simulator.egg-info/dependency_links.txt
data_simulator.egg-info/requires.txt
data_simulator.egg-info/top_level.txt
datasimulator/__init__.py
datasimulator/errors.py
datasimulator/generator.py
datasimulator/graph.py
datasimulator/node.py
datasimulator/submit_data_utils.py
datasimulator/utils.py
tests/__init__.py
tests/conftest.py
tests/test_data_simulator.py