Metadata-Version: 1.0
Name: data-simulator
Version: 0.0.4
Summary: Data simulator
Home-page: UNKNOWN
Author: UNKNOWN
Author-email: UNKNOWN
License: UNKNOWN
Platform: UNKNOWN
